README.rst
setup.py
dms_struct/__init__.py
dms_struct/colorschemes.py
dms_struct/struct_widget.py
dms_struct.egg-info/PKG-INFO
dms_struct.egg-info/SOURCES.txt
dms_struct.egg-info/dependency_links.txt
dms_struct.egg-info/requires.txt
dms_struct.egg-info/top_level.txt