Metadata-Version: 1.1
Name: dms-struct
Version: 0.2.1
Summary: Visualize deep mutational scanning on protein structure.
Home-page: https://github.com/jbloomlab/dms_struct
Author: `the Bloom lab <https://research.fhcrc.org/bloom/en.html>`_
Author-email: jbloom@fredhutch.org
License: GPLv3
Download-URL: https://github.com/jbloomlab/dms_struct/tarball/0.2.1
Platform: Linux and Mac OS X.
